[{"name": "Tars", "stargazerCount": 9261, "forkCount": 2092, "description": "Tars is a high-performance RPC framework based on name service and Tars protocol, also integrated administration platform, and implemented hosting-service via flexible schedule."}, {"name": "TarsGo", "stargazerCount": 2906, "forkCount": 473, "description": "A  high performance microservice  framework  in golang. A linux foundation project."}, {"name": "TarsJava", "stargazerCount": 344, "forkCount": 145, "description": "Java language framework rpc source code implementation"}, {"name": "TarsCpp", "stargazerCount": 328, "forkCount": 206, "description": "C++ language framework rpc source code implementation"}, {"name": "TarsFramework", "stargazerCount": 140, "forkCount": 133, "description": "Tars Basic service framework"}, {"name": "TarsWeb", "stargazerCount": 115, "forkCount": 86, "description": "TARS Projects Dashboard"}, {"name": "TarsDocs", "stargazerCount": 107, "forkCount": 58, "description": "The documentations of TARS"}, {"name": "TarsDocker", "stargazerCount": 81, "forkCount": 26, "description": "Tars Docker  images"}, {"name": "K8STARS", "stargazerCount": 55, "forkCount": 12, "description": "Native Kubernetes  Solution for TARS Services"}, {"name": "TarsTup", "stargazerCount": 49, "forkCount": 17, "description": "Tars tup protocol"}]